mkl_umath/__init__.py
mkl_umath/_init_helper.py
mkl_umath/_patch.cpython-311-x86_64-linux-gnu.so
mkl_umath/_ufuncs.cpython-311-x86_64-linux-gnu.so
mkl_umath/_version.py
mkl_umath/generate_umath.py
mkl_umath/generate_umath_doc.py
mkl_umath/libmkl_umath_loops.so
mkl_umath/ufunc_docstrings_numpy1.py
mkl_umath/ufunc_docstrings_numpy2.py
mkl_umath/tests/test_basic.py
mkl_umath-0.3.1.dist-info/licenses/LICENSE.txt
mkl_umath-0.3.1.dist-info/METADATA
mkl_umath-0.3.1.dist-info/WHEEL
mkl_umath-0.3.1.dist-info/top_level.txt
mkl_umath-0.3.1.dist-info/RECORD
