Metadata-Version: 2.4
Name: mkl_umath
Version: 0.3.1
Summary: Intel (R) MKL-based universal functions for NumPy arrays
Author-email: Intel Corporation <scripting@intel.com>
License-Expression: BSD-3-Clause
Project-URL: Download, http://github.com/IntelPython/mkl_umath
Project-URL: Homepage, http://github.com/IntelPython/mkl_umath
Keywords: mkl_umath
Classifier: Development Status :: 5 - Production/Stable
Classifier: Intended Audience :: Science/Research
Classifier: Intended Audience :: Developers
Classifier: Programming Language :: C
Classifier: Programming Language :: Python
Classifier: Programming Language :: Python :: 3
Classifier: Programming Language :: Python :: 3.9
Classifier: Programming Language :: Python :: 3.10
Classifier: Programming Language :: Python :: 3.11
Classifier: Programming Language :: Python :: 3.12
Classifier: Programming Language :: Python :: 3.13
Classifier: Programming Language :: Python :: 3.14
Classifier: Programming Language :: Python :: Implementation :: CPython
Classifier: Topic :: Software Development
Classifier: Topic :: Scientific/Engineering
Classifier: Operating System :: Microsoft :: Windows
Classifier: Operating System :: POSIX
Classifier: Operating System :: Unix
Requires-Python: <3.15,>=3.9
License-File: LICENSE.txt
Requires-Dist: mkl-service
Provides-Extra: test
Dynamic: license-file
Requires-Dist: intel-cmplr-lib-rt
Requires-Dist: numpy >=2.3.2,<3.0a0
